rekor_monitor/__init__.py
rekor_monitor/main.py
rekor_monitor/merkle_proof.py
rekor_monitor/util.py
rekor_monitor-4.0.1.dist-info/LICENSE
rekor_monitor-4.0.1.dist-info/METADATA
rekor_monitor-4.0.1.dist-info/WHEEL
rekor_monitor-4.0.1.dist-info/entry_points.txt
rekor_monitor-4.0.1.dist-info/RECORD
