Metadata-Version: 2.1
Name: rekor-monitor
Version: 4.0.1
Summary: An auditing system for Sigstore signatures
Author: Nate Lavoy
Author-email: nl2587@nyu.edu
Requires-Python: >=3.13,<4.0
Classifier: Programming Language :: Python :: 3
Classifier: Programming Language :: Python :: 3.13
Requires-Dist: cryptography (>=43.0.3,<44.0.0)
Requires-Dist: jsonschema (>=4.23.0,<5.0.0)
Requires-Dist: pre-commit (>=4.0.1,<5.0.0)
Requires-Dist: requests (>=2.32.3,<3.0.0)
